nothingburger/__init__.py
nothingburger/chains.py
nothingburger/cli.py
nothingburger/instructions.py
nothingburger/memory.py
nothingburger/model_loader.py
nothingburger/parsers.py
nothingburger/templates.py
nothingburger/tools.py
nothingburger/types.py
nothingburger-0.0.1.dist-info/METADATA
nothingburger-0.0.1.dist-info/WHEEL
nothingburger-0.0.1.dist-info/top_level.txt
nothingburger-0.0.1.dist-info/RECORD
