Metadata-Version: 2.4
Name: nothingburger
Version: 0.0.1
Summary: Minimalistic man-made burgers of data and words for interfacing with LLMs and beyond
Author: Keyton Stanier
License: idfk yet
Keywords: nothing,burger,llm,chain,text-generation
Requires-Python: >=3.9
Requires-Dist: python-dotenv
Requires-Dist: Jinja2
Requires-Dist: llama-cpp-python
Requires-Dist: ctransformers
Requires-Dist: openai
Requires-Dist: transformers
Requires-Dist: ollama
Requires-Dist: zulip
Requires-Dist: mattermostdriver
Requires-Dist: mautrix
Requires-Dist: selenium
Requires-Dist: pandoc
Requires-Dist: chromadb
Requires-Dist: psycopg2-binary
